taskiq_rate_limiter/__init__.py
taskiq_rate_limiter/py.typed
taskiq_rate_limiter/rate_limit_middleware.py
taskiq_rate_limiter-0.1.0b2.dist-info/WHEEL
taskiq_rate_limiter-0.1.0b2.dist-info/METADATA
taskiq_rate_limiter-0.1.0b2.dist-info/RECORD
