Metadata-Version: 2.3
Name: taskiq-rate-limiter
Version: 0.1.0b2
Summary: An advanced async rate limiter middleware for Taskiq (Python). Features configurable pacing strategies (adaptive smoothing vs. fixed throughput), burst control, and task throttling.
Author: Artimes Phoenix
Author-email: Artimes Phoenix <artimesphoenix@gmail.com>
License: MIT License
Requires-Dist: taskiq>=0.11.18
Maintainer: Artimes Phoenix
Maintainer-email: Artimes Phoenix <artimesphoenix@gmail.com>
Requires-Python: >=3.10
